asn1crypto_tests/__init__.py
asn1crypto_tests/__main__.py
asn1crypto_tests/_unittest_compat.py
asn1crypto_tests/test_algos.py
asn1crypto_tests/test_cms.py
asn1crypto_tests/test_core.py
asn1crypto_tests/test_crl.py
asn1crypto_tests/test_csr.py
asn1crypto_tests/test_init.py
asn1crypto_tests/test_keys.py
asn1crypto_tests/test_ocsp.py
asn1crypto_tests/test_parser.py
asn1crypto_tests/test_pem.py
asn1crypto_tests/test_pkcs12.py
asn1crypto_tests/test_tsp.py
asn1crypto_tests/test_util.py
asn1crypto_tests/test_x509.py
asn1crypto_tests/unittest_data.py
asn1crypto_tests/fixtures/.DS_Store
asn1crypto_tests/fixtures/9999-years-rsa-cert.pem
asn1crypto_tests/fixtures/DSAParametersInheritedCACert.crt
asn1crypto_tests/fixtures/admin.ch.crt
asn1crypto_tests/fixtures/aesccm_algo.der
asn1crypto_tests/fixtures/certbag.der
asn1crypto_tests/fixtures/cms-compressed.der
asn1crypto_tests/fixtures/cms-compressed.pem
asn1crypto_tests/fixtures/cms-digested.der
asn1crypto_tests/fixtures/cms-digested.pem
asn1crypto_tests/fixtures/cms-encrypted.der
asn1crypto_tests/fixtures/cms-encrypted.pem
asn1crypto_tests/fixtures/cms-enveloped.der
asn1crypto_tests/fixtures/cms-enveloped.pem
asn1crypto_tests/fixtures/cms-signed-digested.der
asn1crypto_tests/fixtures/cms-signed-digested.pem
asn1crypto_tests/fixtures/cms-signed-indefinite-length.der
asn1crypto_tests/fixtures/cms-signed.der
asn1crypto_tests/fixtures/cms-signed.pem
asn1crypto_tests/fixtures/eid2011.crl
asn1crypto_tests/fixtures/example-attr-cert.der
asn1crypto_tests/fixtures/invalid_email_tag.pem
asn1crypto_tests/fixtures/meca2_compressed.der
asn1crypto_tests/fixtures/message.der
asn1crypto_tests/fixtures/message.pem
asn1crypto_tests/fixtures/message.txt
asn1crypto_tests/fixtures/mozilla-generated-by-openssl.pkcs7.der
asn1crypto_tests/fixtures/ocsp-with-pkup.pem
asn1crypto_tests/fixtures/ocsp_request
asn1crypto_tests/fixtures/ocsp_response
asn1crypto_tests/fixtures/pkcs7-signed-digested.der
asn1crypto_tests/fixtures/pkcs7-signed-digested.pem
asn1crypto_tests-1.5.1.dist-info/LICENSE
asn1crypto_tests-1.5.1.dist-info/METADATA
asn1crypto_tests-1.5.1.dist-info/WHEEL
asn1crypto_tests-1.5.1.dist-info/top_level.txt
asn1crypto_tests-1.5.1.dist-info/RECORD
